{
  "type": "FeatureCollection",
  "features": [
    {
      "type": "Feature",
      "id": "245362461",
      "geometry": {
        "type": "Point",
        "coordinates": [
          104.27815717999998,
          15.242956049045763
        ]
      },
      "properties": {
        "activity_id": "245362461",
        "confirm_status": "ที่เข้าเงื่อนไข",
        "model_result_text": "แปลงเกษตรจากคำร้อง กษ.01 ที่เข้าเงื่อนไข น้ำท่วมมิดต้นข้าวติดต่อกันมากกว่า 5 วัน",
        "address": "สถานที่: หมู่ที่ 5 ตำบลคูซอด อำเภอเมืองศรีสะเกษ จังหวัดศรีสะเกษ",
        "rice_variety": "ขาวดอกมะลิ 105",
        "dates": {
          "plant_str": "10/06/2568",
          "harvest_str": "23/11/2568"
        },
        "image_filename": "245362461.png"
      }
    },
    {
      "type": "Feature",
      "id": "243162365",
      "geometry": {
        "type": "Point",
        "coordinates": [
          104.18446161152588,
          15.27777441696087
        ]
      },
      "properties": {
        "activity_id": "243162365",
        "confirm_status": "ที่เข้าเงื่อนไข",
        "model_result_text": "แปลงเกษตรจากคำร้อง กษ.01 ที่เข้าเงื่อนไข น้ำท่วมมิดต้นข้าวติดต่อกันมากกว่า 5 วัน",
        "address": "สถานที่: หมู่ที่ 4 ตำบลหนองอึ่ง อำเภอราษีไศล จังหวัดศรีสะเกษ",
        "rice_variety": "ขาวดอกมะลิ 105",
        "dates": {
          "plant_str": "02/05/2568",
          "harvest_str": "20/11/2568"
        },
        "image_filename": "243162365.png"
      }
    },
    {
      "type": "Feature",
      "id": "242173535",
      "geometry": {
        "type": "Point",
        "coordinates": [
          104.1139134625735,
          15.330473651574776
        ]
      },
      "properties": {
        "activity_id": "242173535",
        "confirm_status": "ที่เข้าเงื่อนไข",
        "model_result_text": "แปลงเกษตรจากคำร้อง กษ.01 ที่เข้าเงื่อนไข น้ำท่วมมิดต้นข้าวติดต่อกันมากกว่า 5 วัน",
        "address": "สถานที่: หมู่ที่ 6 ตำบลบัวหุ่ง อำเภอราษีไศล จังหวัดศรีสะเกษ",
        "rice_variety": "กข15",
        "dates": {
          "plant_str": "18/05/2568",
          "harvest_str": "20/10/2568"
        },
        "image_filename": "242173535.png"
      }
    },
    {
      "type": "Feature",
      "id": "237224826",
      "geometry": {
        "type": "Point",
        "coordinates": [
          104.00760587465298,
          14.983203011497023
        ]
      },
      "properties": {
        "activity_id": "237224826",
        "confirm_status": "ที่เข้าเงื่อนไข",
        "model_result_text": "แปลงเกษตรจากคำร้อง กษ.01 ที่เข้าเงื่อนไข น้ำท่วมมิดต้นข้าวติดต่อกันมากกว่า 5 วัน",
        "address": "สถานที่: หมู่ที่ 11 ตำบลจานแสนไชย อำเภอห้วยทับทัน จังหวัดศรีสะเกษ",
        "rice_variety": "ขาวดอกมะลิ 105",
        "dates": {
          "plant_str": "20/05/2568",
          "harvest_str": "20/11/2568"
        },
        "image_filename": "237224826.png"
      }
    },
    {
      "type": "Feature",
      "id": "241393402",
      "geometry": {
        "type": "Point",
        "coordinates": [
          103.99606838886464,
          14.97599359002473
        ]
      },
      "properties": {
        "activity_id": "241393402",
        "confirm_status": "ที่เข้าเงื่อนไข",
        "model_result_text": "แปลงเกษตรจากคำร้อง กษ.01 ที่เข้าเงื่อนไข น้ำท่วมมิดต้นข้าวติดต่อกันมากกว่า 5 วัน",
        "address": "สถานที่: หมู่ที่ 7 ตำบลจานแสนไชย อำเภอห้วยทับทัน จังหวัดศรีสะเกษ",
        "rice_variety": "ขาวดอกมะลิ 105",
        "dates": {
          "plant_str": "09/05/2568",
          "harvest_str": "15/11/2568"
        },
        "image_filename": "241393402.png"
      }
    }
  ]
}